{"cam1": {"Walking_Man": [618.13, 431.00], "Ch42__Eyelashes": [618.13, 431.00], "Ch42_Body1": [618.13, 431.00], "Ch42_Hair1": [618.13, 431.00], "Ch42_Shirt": [618.13, 431.00], "Ch42_Shorts": [618.13, 431.00], "Ch42_Sneakers": [618.13, 431.00], "mixamorig:Hips": [616.82, 486.58], "mixamorig:LeftUpLeg": [621.95, 484.37], "mixamorig:LeftLeg": [623.39, 459.19], "mixamorig:LeftFoot": [619.67, 440.98], "mixamorig:LeftToeBase": [624.81, 429.82], "mixamorig:LeftToe_End": [627.04, 428.02], "mixamorig:RightUpLeg": [611.08, 482.22], "mixamorig:RightLeg": [614.11, 454.92], "mixamorig:RightFoot": [611.92, 440.97], "mixamorig:RightToeBase": [610.80, 428.11], "mixamorig:RightToe_End": [611.73, 424.92], "mixamorig:Spine": [616.57, 493.32], "mixamorig:Spine1": [616.32, 501.28], "mixamorig:Spine2": [616.13, 510.51], "mixamorig:LeftShoulder": [620.00, 520.46], "mixamorig:LeftArm": [627.61, 516.00], "mixamorig:LeftForeArm": [631.99, 500.91], "mixamorig:LeftHand": [634.91, 485.39], "mixamorig:LeftHandIndex1": [635.22, 478.35], "mixamorig:LeftHandIndex2": [634.26, 476.40], "mixamorig:LeftHandIndex3": [632.27, 476.52], "mixamorig:LeftHandIndex4": [630.58, 476.65], "mixamorig:LeftHandMiddle1": [636.14, 478.59], "mixamorig:LeftHandMiddle2": [634.47, 477.06], "mixamorig:LeftHandMiddle3": [632.91, 478.60], "mixamorig:LeftHandMiddle4": [631.52, 479.99], "mixamorig:LeftHandPinky1": [636.96, 480.04], "mixamorig:LeftHandPinky2": [635.50, 479.14], "mixamorig:LeftHandPinky3": [634.43, 480.24], "mixamorig:LeftHandPinky4": [633.54, 481.17], "mixamorig:LeftHandRing1": [636.75, 478.91], "mixamorig:LeftHandRing2": [635.39, 477.68], "mixamorig:LeftHandRing3": [634.10, 479.02], "mixamorig:LeftHandRing4": [633.03, 480.15], "mixamorig:LeftHandThumb1": [633.78, 482.87], "mixamorig:LeftHandThumb2": [632.67, 480.80], "mixamorig:LeftHandThumb3": [631.69, 478.74], "mixamorig:LeftHandThumb4": [630.88, 476.92], "mixamorig:Neck": [616.02, 521.07], "mixamorig:Head": [616.61, 524.14], "mixamorig:HeadTop_End": [618.65, 538.32], "mixamorig:RightShoulder": [611.94, 519.32], "mixamorig:RightArm": [604.92, 513.23], "mixamorig:RightForeArm": [600.66, 496.76], "mixamorig:RightHand": [599.92, 480.97], "mixamorig:RightHandIndex1": [601.26, 474.30], "mixamorig:RightHandIndex2": [602.36, 472.63], "mixamorig:RightHandIndex3": [603.71, 473.56], "mixamorig:RightHandIndex4": [604.84, 474.38], "mixamorig:RightHandMiddle1": [599.74, 474.24], "mixamorig:RightHandMiddle2": [601.14, 472.67], "mixamorig:RightHandMiddle3": [602.35, 474.18], "mixamorig:RightHandMiddle4": [603.40, 475.51], "mixamorig:RightHandPinky1": [597.63, 474.75], "mixamorig:RightHandPinky2": [598.67, 473.44], "mixamorig:RightHandPinky3": [599.47, 474.63], "mixamorig:RightHandPinky4": [600.13, 475.62], "mixamorig:RightHandRing1": [598.58, 474.11], "mixamorig:RightHandRing2": [599.71, 472.77], "mixamorig:RightHandRing3": [600.73, 474.15], "mixamorig:RightHandRing4": [601.55, 475.28], "mixamorig:RightHandThumb1": [601.82, 478.80], "mixamorig:RightHandThumb2": [603.05, 476.79], "mixamorig:RightHandThumb3": [603.75, 474.56], "mixamorig:RightHandThumb4": [604.27, 472.64]},  "cam2": {"Walking_Man": [998.72, 233.46], "Ch42__Eyelashes": [998.72, 233.46], "Ch42_Body1": [998.72, 233.46], "Ch42_Hair1": [998.72, 233.46], "Ch42_Shirt": [998.72, 233.46], "Ch42_Shorts": [998.72, 233.46], "Ch42_Sneakers": [998.72, 233.46], "mixamorig:Hips": [998.26, 354.22], "mixamorig:LeftUpLeg": [1010.14, 346.52], "mixamorig:LeftLeg": [1007.33, 294.19], "mixamorig:LeftFoot": [1012.81, 248.77], "mixamorig:LeftToeBase": [1001.63, 230.80], "mixamorig:LeftToe_End": [995.60, 230.69], "mixamorig:RightUpLeg": [988.26, 347.36], "mixamorig:RightLeg": [972.23, 300.10], "mixamorig:RightFoot": [990.28, 259.08], "mixamorig:RightToeBase": [976.10, 238.34], "mixamorig:RightToe_End": [968.01, 236.25], "mixamorig:Spine": [999.14, 367.43], "mixamorig:Spine1": [1000.22, 382.83], "mixamorig:Spine2": [1001.52, 400.44], "mixamorig:LeftShoulder": [1010.75, 418.34], "mixamorig:LeftArm": [1021.80, 409.72], "mixamorig:LeftForeArm": [1034.59, 375.72], "mixamorig:LeftHand": [1026.60, 347.70], "mixamorig:LeftHandIndex1": [1019.23, 335.96], "mixamorig:LeftHandIndex2": [1017.30, 332.12], "mixamorig:LeftHandIndex3": [1015.64, 332.20], "mixamorig:LeftHandIndex4": [1014.38, 332.25], "mixamorig:LeftHandMiddle1": [1023.22, 335.04], "mixamorig:LeftHandMiddle2": [1020.82, 331.96], "mixamorig:LeftHandMiddle3": [1020.35, 334.78], "mixamorig:LeftHandMiddle4": [1020.00, 337.28], "mixamorig:LeftHandPinky1": [1030.30, 335.26], "mixamorig:LeftHandPinky2": [1028.48, 333.36], "mixamorig:LeftHandPinky3": [1027.75, 335.59], "mixamorig:LeftHandPinky4": [1027.15, 337.46], "mixamorig:LeftHandRing1": [1026.60, 334.43], "mixamorig:LeftHandRing2": [1024.77, 331.88], "mixamorig:LeftHandRing3": [1024.09, 334.50], "mixamorig:LeftHandRing4": [1023.54, 336.69], "mixamorig:LeftHandThumb1": [1021.24, 344.15], "mixamorig:LeftHandThumb2": [1017.94, 340.64], "mixamorig:LeftHandThumb3": [1015.30, 336.92], "mixamorig:LeftHandThumb4": [1013.02, 333.66], "mixamorig:Neck": [1003.04, 420.27], "mixamorig:Head": [1001.53, 427.16], "mixamorig:HeadTop_End": [992.26, 458.98], "mixamorig:RightShoulder": [995.46, 417.61], "mixamorig:RightArm": [981.70, 407.91], "mixamorig:RightForeArm": [979.43, 375.31], "mixamorig:RightHand": [970.51, 348.56], "mixamorig:RightHandIndex1": [962.87, 339.81], "mixamorig:RightHandIndex2": [964.17, 336.28], "mixamorig:RightHandIndex3": [968.28, 336.61], "mixamorig:RightHandIndex4": [971.89, 336.88], "mixamorig:RightHandMiddle1": [962.65, 339.17], "mixamorig:RightHandMiddle2": [964.65, 335.62], "mixamorig:RightHandMiddle3": [968.97, 336.93], "mixamorig:RightHandMiddle4": [972.80, 338.09], "mixamorig:RightHandPinky1": [964.28, 338.49], "mixamorig:RightHandPinky2": [965.40, 335.76], "mixamorig:RightHandPinky3": [968.07, 337.08], "mixamorig:RightHandPinky4": [970.32, 338.18], "mixamorig:RightHandRing1": [962.72, 338.41], "mixamorig:RightHandRing2": [964.18, 335.48], "mixamorig:RightHandRing3": [967.55, 336.92], "mixamorig:RightHandRing4": [970.33, 338.09], "mixamorig:RightHandThumb1": [969.43, 345.66], "mixamorig:RightHandThumb2": [968.33, 342.76], "mixamorig:RightHandThumb3": [967.28, 339.14], "mixamorig:RightHandThumb4": [966.16, 336.09]}}