{"cam1": {"Walking_Man": [631.94, 409.98], "Ch42__Eyelashes": [631.94, 409.98], "Ch42_Body1": [631.94, 409.98], "Ch42_Hair1": [631.94, 409.98], "Ch42_Shirt": [631.94, 409.98], "Ch42_Shorts": [631.94, 409.98], "Ch42_Sneakers": [631.94, 409.98], "mixamorig:Hips": [630.95, 466.20], "mixamorig:LeftUpLeg": [635.76, 464.14], "mixamorig:LeftLeg": [639.65, 439.43], "mixamorig:LeftFoot": [627.84, 437.68], "mixamorig:LeftToeBase": [628.51, 430.80], "mixamorig:LeftToe_End": [630.25, 426.33], "mixamorig:RightUpLeg": [624.98, 461.62], "mixamorig:RightLeg": [631.67, 433.62], "mixamorig:RightFoot": [632.21, 412.52], "mixamorig:RightToeBase": [635.50, 399.94], "mixamorig:RightToe_End": [637.33, 397.70], "mixamorig:Spine": [631.01, 473.11], "mixamorig:Spine1": [630.89, 481.24], "mixamorig:Spine2": [630.51, 490.67], "mixamorig:LeftShoulder": [633.98, 501.20], "mixamorig:LeftArm": [642.22, 497.25], "mixamorig:LeftForeArm": [651.72, 481.44], "mixamorig:LeftHand": [656.07, 466.12], "mixamorig:LeftHandIndex1": [657.89, 461.03], "mixamorig:LeftHandIndex2": [657.49, 458.74], "mixamorig:LeftHandIndex3": [655.47, 458.36], "mixamorig:LeftHandIndex4": [653.75, 458.02], "mixamorig:LeftHandMiddle1": [659.13, 460.70], "mixamorig:LeftHandMiddle2": [657.91, 458.52], "mixamorig:LeftHandMiddle3": [656.23, 459.65], "mixamorig:LeftHandMiddle4": [654.73, 460.66], "mixamorig:LeftHandPinky1": [660.26, 460.65], "mixamorig:LeftHandPinky2": [659.07, 459.14], "mixamorig:LeftHandPinky3": [657.87, 460.09], "mixamorig:LeftHandPinky4": [656.87, 460.89], "mixamorig:LeftHandRing1": [659.99, 460.43], "mixamorig:LeftHandRing2": [659.00, 458.63], "mixamorig:LeftHandRing3": [657.57, 459.74], "mixamorig:LeftHandRing4": [656.38, 460.66], "mixamorig:LeftHandThumb1": [655.31, 464.25], "mixamorig:LeftHandThumb2": [654.67, 462.21], "mixamorig:LeftHandThumb3": [654.23, 460.05], "mixamorig:LeftHandThumb4": [653.89, 458.18], "mixamorig:Neck": [629.79, 501.44], "mixamorig:Head": [630.21, 504.78], "mixamorig:HeadTop_End": [631.90, 520.04], "mixamorig:RightShoulder": [625.63, 499.27], "mixamorig:RightArm": [618.83, 492.16], "mixamorig:RightForeArm": [612.58, 479.50], "mixamorig:RightHand": [611.77, 464.98], "mixamorig:RightHandIndex1": [612.74, 458.31], "mixamorig:RightHandIndex2": [613.43, 457.34], "mixamorig:RightHandIndex3": [615.03, 458.30], "mixamorig:RightHandIndex4": [616.38, 459.17], "mixamorig:RightHandMiddle1": [611.18, 459.00], "mixamorig:RightHandMiddle2": [612.20, 458.20], "mixamorig:RightHandMiddle3": [613.88, 459.69], "mixamorig:RightHandMiddle4": [615.33, 461.00], "mixamorig:RightHandPinky1": [609.04, 461.09], "mixamorig:RightHandPinky2": [609.82, 460.30], "mixamorig:RightHandPinky3": [610.98, 461.37], "mixamorig:RightHandPinky4": [611.95, 462.27], "mixamorig:RightHandRing1": [609.98, 459.61], "mixamorig:RightHandRing2": [610.84, 458.91], "mixamorig:RightHandRing3": [612.27, 460.17], "mixamorig:RightHandRing4": [613.43, 461.21], "mixamorig:RightHandThumb1": [613.59, 462.68], "mixamorig:RightHandThumb2": [614.86, 460.90], "mixamorig:RightHandThumb3": [615.46, 459.37], "mixamorig:RightHandThumb4": [615.89, 458.00]},  "cam2": {"Walking_Man": [856.18, 261.16], "Ch42__Eyelashes": [856.18, 261.16], "Ch42_Body1": [856.18, 261.16], "Ch42_Hair1": [856.18, 261.16], "Ch42_Shirt": [856.18, 261.16], "Ch42_Shorts": [856.18, 261.16], "Ch42_Sneakers": [856.18, 261.16], "mixamorig:Hips": [855.59, 350.96], "mixamorig:LeftUpLeg": [863.23, 344.97], "mixamorig:LeftLeg": [865.04, 305.77], "mixamorig:LeftFoot": [884.96, 289.71], "mixamorig:LeftToeBase": [894.29, 272.95], "mixamorig:LeftToe_End": [893.64, 265.97], "mixamorig:RightUpLeg": [849.31, 346.10], "mixamorig:RightLeg": [834.60, 312.62], "mixamorig:RightFoot": [838.22, 276.63], "mixamorig:RightToeBase": [825.15, 264.29], "mixamorig:RightToe_End": [818.99, 264.65], "mixamorig:Spine": [856.30, 360.89], "mixamorig:Spine1": [856.95, 372.49], "mixamorig:Spine2": [857.48, 385.72], "mixamorig:LeftShoulder": [862.51, 399.36], "mixamorig:LeftArm": [868.55, 393.44], "mixamorig:LeftForeArm": [873.45, 370.33], "mixamorig:LeftHand": [860.07, 354.32], "mixamorig:LeftHandIndex1": [851.02, 351.39], "mixamorig:LeftHandIndex2": [848.59, 348.97], "mixamorig:LeftHandIndex3": [848.36, 348.04], "mixamorig:LeftHandIndex4": [848.25, 347.20], "mixamorig:LeftHandMiddle1": [853.09, 350.09], "mixamorig:LeftHandMiddle2": [850.75, 347.58], "mixamorig:LeftHandMiddle3": [852.20, 348.24], "mixamorig:LeftHandMiddle4": [853.53, 348.80], "mixamorig:LeftHandPinky1": [857.56, 347.97], "mixamorig:LeftHandPinky2": [855.94, 346.13], "mixamorig:LeftHandPinky3": [856.78, 346.93], "mixamorig:LeftHandPinky4": [857.49, 347.60], "mixamorig:LeftHandRing1": [854.92, 348.92], "mixamorig:LeftHandRing2": [853.06, 346.80], "mixamorig:LeftHandRing3": [854.18, 347.65], "mixamorig:LeftHandRing4": [855.12, 348.36], "mixamorig:LeftHandThumb1": [855.53, 353.52], "mixamorig:LeftHandThumb2": [852.30, 351.85], "mixamorig:LeftHandThumb3": [849.38, 349.88], "mixamorig:LeftHandThumb4": [846.82, 348.21], "mixamorig:Neck": [857.88, 400.55], "mixamorig:Head": [856.74, 405.82], "mixamorig:HeadTop_End": [849.97, 429.98], "mixamorig:RightShoulder": [853.48, 398.32], "mixamorig:RightArm": [845.82, 390.16], "mixamorig:RightForeArm": [851.97, 367.99], "mixamorig:RightHand": [852.08, 346.91], "mixamorig:RightHandIndex1": [852.10, 337.30], "mixamorig:RightHandIndex2": [854.05, 334.95], "mixamorig:RightHandIndex3": [856.61, 335.33], "mixamorig:RightHandIndex4": [858.88, 335.69], "mixamorig:RightHandMiddle1": [852.47, 337.83], "mixamorig:RightHandMiddle2": [854.87, 335.57], "mixamorig:RightHandMiddle3": [857.38, 336.76], "mixamorig:RightHandMiddle4": [859.61, 337.83], "mixamorig:RightHandPinky1": [853.96, 339.69], "mixamorig:RightHandPinky2": [855.57, 337.84], "mixamorig:RightHandPinky3": [856.97, 338.91], "mixamorig:RightHandPinky4": [858.14, 339.81], "mixamorig:RightHandRing1": [853.02, 338.20], "mixamorig:RightHandRing2": [854.92, 336.32], "mixamorig:RightHandRing3": [856.75, 337.50], "mixamorig:RightHandRing4": [858.26, 338.47], "mixamorig:RightHandThumb1": [852.75, 343.56], "mixamorig:RightHandThumb2": [853.64, 340.73], "mixamorig:RightHandThumb3": [854.99, 337.86], "mixamorig:RightHandThumb4": [856.01, 335.36]}}