{"cam1": {"Walking_Man": [665.22, 373.08], "Ch42__Eyelashes": [665.22, 373.08], "Ch42_Body1": [665.22, 373.08], "Ch42_Hair1": [665.22, 373.08], "Ch42_Shirt": [665.22, 373.08], "Ch42_Shorts": [665.22, 373.08], "Ch42_Sneakers": [665.22, 373.08], "mixamorig:Hips": [667.07, 433.32], "mixamorig:LeftUpLeg": [672.48, 431.36], "mixamorig:LeftLeg": [672.02, 404.53], "mixamorig:LeftFoot": [665.99, 385.72], "mixamorig:LeftToeBase": [672.02, 372.70], "mixamorig:LeftToe_End": [674.91, 370.24], "mixamorig:RightUpLeg": [660.43, 428.25], "mixamorig:RightLeg": [664.08, 397.28], "mixamorig:RightFoot": [660.47, 380.64], "mixamorig:RightToeBase": [660.06, 365.86], "mixamorig:RightToe_End": [661.51, 362.21], "mixamorig:Spine": [667.10, 440.73], "mixamorig:Spine1": [667.20, 449.50], "mixamorig:Spine2": [667.44, 459.70], "mixamorig:LeftShoulder": [672.26, 470.92], "mixamorig:LeftArm": [680.77, 466.22], "mixamorig:LeftForeArm": [685.24, 450.08], "mixamorig:LeftHand": [688.45, 432.35], "mixamorig:LeftHandIndex1": [688.80, 424.27], "mixamorig:LeftHandIndex2": [687.64, 422.03], "mixamorig:LeftHandIndex3": [685.30, 422.17], "mixamorig:LeftHandIndex4": [683.31, 422.31], "mixamorig:LeftHandMiddle1": [689.77, 424.57], "mixamorig:LeftHandMiddle2": [687.78, 422.80], "mixamorig:LeftHandMiddle3": [685.97, 424.56], "mixamorig:LeftHandMiddle4": [684.36, 426.15], "mixamorig:LeftHandPinky1": [690.56, 426.25], "mixamorig:LeftHandPinky2": [688.82, 425.21], "mixamorig:LeftHandPinky3": [687.61, 426.47], "mixamorig:LeftHandPinky4": [686.59, 427.53], "mixamorig:LeftHandRing1": [690.39, 424.94], "mixamorig:LeftHandRing2": [688.76, 423.53], "mixamorig:LeftHandRing3": [687.29, 425.06], "mixamorig:LeftHandRing4": [686.05, 426.34], "mixamorig:LeftHandThumb1": [687.18, 429.46], "mixamorig:LeftHandThumb2": [685.87, 427.09], "mixamorig:LeftHandThumb3": [684.69, 424.72], "mixamorig:LeftHandThumb4": [683.73, 422.64], "mixamorig:Neck": [667.84, 471.40], "mixamorig:Head": [668.83, 474.65], "mixamorig:HeadTop_End": [672.63, 489.74], "mixamorig:RightShoulder": [663.17, 469.27], "mixamorig:RightArm": [655.02, 462.11], "mixamorig:RightForeArm": [648.90, 444.45], "mixamorig:RightHand": [646.95, 427.14], "mixamorig:RightHandIndex1": [648.26, 419.12], "mixamorig:RightHandIndex2": [649.38, 417.36], "mixamorig:RightHandIndex3": [650.97, 418.53], "mixamorig:RightHandIndex4": [652.29, 419.56], "mixamorig:RightHandMiddle1": [646.47, 419.28], "mixamorig:RightHandMiddle2": [647.96, 417.69], "mixamorig:RightHandMiddle3": [649.41, 419.54], "mixamorig:RightHandMiddle4": [650.68, 421.16], "mixamorig:RightHandPinky1": [644.00, 420.35], "mixamorig:RightHandPinky2": [645.10, 418.98], "mixamorig:RightHandPinky3": [646.08, 420.37], "mixamorig:RightHandPinky4": [646.89, 421.54], "mixamorig:RightHandRing1": [645.11, 419.34], "mixamorig:RightHandRing2": [646.30, 417.96], "mixamorig:RightHandRing3": [647.54, 419.60], "mixamorig:RightHandRing4": [648.55, 420.93], "mixamorig:RightHandThumb1": [649.06, 424.48], "mixamorig:RightHandThumb2": [650.35, 422.06], "mixamorig:RightHandThumb3": [650.98, 419.51], "mixamorig:RightHandThumb4": [651.42, 417.31]},  "cam2": {"Walking_Man": [764.22, 260.95], "Ch42__Eyelashes": [764.22, 260.95], "Ch42_Body1": [764.22, 260.95], "Ch42_Hair1": [764.22, 260.95], "Ch42_Shirt": [764.22, 260.95], "Ch42_Shorts": [764.22, 260.95], "Ch42_Sneakers": [764.22, 260.95], "mixamorig:Hips": [763.96, 355.34], "mixamorig:LeftUpLeg": [770.57, 349.40], "mixamorig:LeftLeg": [769.78, 308.62], "mixamorig:LeftFoot": [776.87, 273.21], "mixamorig:LeftToeBase": [765.11, 259.52], "mixamorig:LeftToe_End": [759.04, 259.60], "mixamorig:RightUpLeg": [759.16, 349.91], "mixamorig:RightLeg": [744.10, 313.44], "mixamorig:RightFoot": [756.22, 279.05], "mixamorig:RightToeBase": [743.42, 264.18], "mixamorig:RightToe_End": [736.34, 263.34], "mixamorig:Spine": [764.64, 365.67], "mixamorig:Spine1": [765.44, 377.71], "mixamorig:Spine2": [766.35, 391.48], "mixamorig:LeftShoulder": [771.24, 405.40], "mixamorig:LeftArm": [775.56, 398.62], "mixamorig:LeftForeArm": [783.00, 372.42], "mixamorig:LeftHand": [773.26, 351.59], "mixamorig:LeftHandIndex1": [766.66, 343.02], "mixamorig:LeftHandIndex2": [765.57, 340.05], "mixamorig:LeftHandIndex3": [765.59, 339.98], "mixamorig:LeftHandIndex4": [765.71, 339.89], "mixamorig:LeftHandMiddle1": [769.10, 342.17], "mixamorig:LeftHandMiddle2": [768.16, 339.73], "mixamorig:LeftHandMiddle3": [768.99, 341.75], "mixamorig:LeftHandMiddle4": [769.76, 343.54], "mixamorig:LeftHandPinky1": [774.04, 342.01], "mixamorig:LeftHandPinky2": [773.51, 340.46], "mixamorig:LeftHandPinky3": [773.78, 342.11], "mixamorig:LeftHandPinky4": [774.02, 343.48], "mixamorig:LeftHandRing1": [771.27, 341.56], "mixamorig:LeftHandRing2": [770.62, 339.54], "mixamorig:LeftHandRing3": [771.10, 341.45], "mixamorig:LeftHandRing4": [771.50, 343.04], "mixamorig:LeftHandThumb1": [769.64, 349.06], "mixamorig:LeftHandThumb2": [767.60, 346.43], "mixamorig:LeftHandThumb3": [765.99, 343.60], "mixamorig:LeftHandThumb4": [764.55, 341.13], "mixamorig:Neck": [767.37, 406.99], "mixamorig:Head": [765.76, 412.34], "mixamorig:HeadTop_End": [757.04, 437.05], "mixamorig:RightShoulder": [763.62, 405.00], "mixamorig:RightArm": [756.64, 397.38], "mixamorig:RightForeArm": [757.95, 371.84], "mixamorig:RightHand": [753.00, 350.37], "mixamorig:RightHandIndex1": [746.75, 342.88], "mixamorig:RightHandIndex2": [747.36, 340.10], "mixamorig:RightHandIndex3": [749.84, 340.42], "mixamorig:RightHandIndex4": [752.04, 340.69], "mixamorig:RightHandMiddle1": [747.52, 342.47], "mixamorig:RightHandMiddle2": [748.57, 339.71], "mixamorig:RightHandMiddle3": [751.25, 340.86], "mixamorig:RightHandMiddle4": [753.63, 341.88], "mixamorig:RightHandPinky1": [750.11, 342.19], "mixamorig:RightHandPinky2": [750.60, 340.05], "mixamorig:RightHandPinky3": [752.22, 341.16], "mixamorig:RightHandPinky4": [753.57, 342.09], "mixamorig:RightHandRing1": [748.30, 341.96], "mixamorig:RightHandRing2": [749.04, 339.66], "mixamorig:RightHandRing3": [751.08, 340.88], "mixamorig:RightHandRing4": [752.76, 341.87], "mixamorig:RightHandThumb1": [751.25, 347.88], "mixamorig:RightHandThumb2": [749.79, 345.44], "mixamorig:RightHandThumb3": [748.77, 342.48], "mixamorig:RightHandThumb4": [747.76, 339.97]}}