{"cam1": {"Running_Man": [654.78, 329.72], "Ch28_Body": [654.78, 329.72], "Ch28_Eyelashes": [654.78, 329.72], "Ch28_Hair": [654.78, 329.72], "Ch28_Hoody": [654.78, 329.72], "Ch28_Pants": [654.78, 329.72], "Ch28_Sneakers": [654.78, 329.72], "mixamorig10:Hips": [653.18, 388.07], "mixamorig10:LeftUpLeg": [656.25, 387.73], "mixamorig10:LeftLeg": [676.05, 361.19], "mixamorig10:LeftFoot": [651.89, 352.07], "mixamorig10:LeftToeBase": [654.17, 343.59], "mixamorig10:LeftToe_End": [657.92, 340.13], "mixamorig10:RightUpLeg": [648.47, 380.91], "mixamorig10:RightLeg": [648.63, 353.35], "mixamorig10:RightFoot": [633.34, 341.52], "mixamorig10:RightToeBase": [642.14, 330.26], "mixamorig10:RightToe_End": [647.02, 328.87], "mixamorig10:Spine": [653.57, 395.36], "mixamorig10:Spine1": [654.50, 403.66], "mixamorig10:Spine2": [656.41, 413.18], "mixamorig10:LeftShoulder": [661.16, 426.06], "mixamorig10:LeftArm": [662.35, 428.53], "mixamorig10:LeftForeArm": [649.80, 422.66], "mixamorig10:LeftHand": [662.94, 410.50], "mixamorig10:LeftHandIndex1": [671.60, 406.96], "mixamorig10:LeftHandIndex2": [673.30, 405.14], "mixamorig10:LeftHandIndex3": [674.35, 403.70], "mixamorig10:LeftHandIndex4": [675.01, 402.61], "mixamorig10:LeftHandMiddle1": [670.54, 405.30], "mixamorig10:LeftHandMiddle2": [672.30, 403.41], "mixamorig10:LeftHandMiddle3": [673.46, 401.84], "mixamorig10:LeftHandMiddle4": [674.21, 400.62], "mixamorig10:LeftHandPinky1": [667.74, 402.87], "mixamorig10:LeftHandPinky2": [669.03, 401.27], "mixamorig10:LeftHandPinky3": [669.73, 400.18], "mixamorig10:LeftHandPinky4": [670.15, 399.41], "mixamorig10:LeftHandRing1": [669.62, 403.71], "mixamorig10:LeftHandRing2": [671.08, 402.14], "mixamorig10:LeftHandRing3": [672.02, 400.92], "mixamorig10:LeftHandRing4": [672.62, 400.03], "mixamorig10:LeftHandThumb1": [666.43, 410.25], "mixamorig10:LeftHandThumb2": [669.09, 409.52], "mixamorig10:LeftHandThumb3": [670.99, 407.83], "mixamorig10:LeftHandThumb4": [672.39, 406.17], "mixamorig10:Neck": [659.54, 423.94], "mixamorig10:Head": [663.61, 428.31], "mixamorig10:HeadTop_End": [675.01, 440.64], "mixamorig10:RightShoulder": [657.06, 419.89], "mixamorig10:RightArm": [650.57, 410.62], "mixamorig10:RightForeArm": [647.19, 387.42], "mixamorig10:RightHand": [666.25, 387.92], "mixamorig10:RightHandIndex1": [675.51, 391.87], "mixamorig10:RightHandIndex2": [678.25, 392.55], "mixamorig10:RightHandIndex3": [680.33, 393.44], "mixamorig10:RightHandIndex4": [681.79, 394.28], "mixamorig10:RightHandMiddle1": [676.14, 389.66], "mixamorig10:RightHandMiddle2": [679.04, 390.38], "mixamorig10:RightHandMiddle3": [681.19, 391.33], "mixamorig10:RightHandMiddle4": [682.73, 392.27], "mixamorig10:RightHandPinky1": [675.55, 385.78], "mixamorig10:RightHandPinky2": [677.81, 386.35], "mixamorig10:RightHandPinky3": [679.31, 387.07], "mixamorig10:RightHandPinky4": [680.35, 387.77], "mixamorig10:RightHandRing1": [676.21, 387.77], "mixamorig10:RightHandRing2": [678.65, 388.38], "mixamorig10:RightHandRing3": [680.49, 389.24], "mixamorig10:RightHandRing4": [681.82, 390.11], "mixamorig10:RightHandThumb1": [669.24, 391.11], "mixamorig10:RightHandThumb2": [671.94, 393.29], "mixamorig10:RightHandThumb3": [674.82, 394.15], "mixamorig10:RightHandThumb4": [677.20, 394.50]},  "cam2": {"Running_Man": [680.60, 221.32], "Ch28_Body": [680.60, 221.32], "Ch28_Eyelashes": [680.60, 221.32], "Ch28_Hair": [680.60, 221.32], "Ch28_Hoody": [680.60, 221.32], "Ch28_Pants": [680.60, 221.32], "Ch28_Sneakers": [680.60, 221.32], "mixamorig10:Hips": [681.95, 345.33], "mixamorig10:LeftUpLeg": [693.36, 337.05], "mixamorig10:LeftLeg": [680.23, 288.86], "mixamorig10:LeftFoot": [693.31, 262.07], "mixamorig10:LeftToeBase": [699.77, 237.69], "mixamorig10:LeftToe_End": [699.14, 229.41], "mixamorig10:RightUpLeg": [671.70, 338.09], "mixamorig10:RightLeg": [672.48, 281.24], "mixamorig10:RightFoot": [690.55, 244.76], "mixamorig10:RightToeBase": [680.57, 226.20], "mixamorig10:RightToe_End": [675.77, 225.68], "mixamorig10:Spine": [682.06, 359.65], "mixamorig10:Spine1": [681.28, 376.34], "mixamorig10:Spine2": [680.14, 395.42], "mixamorig10:LeftShoulder": [688.72, 415.31], "mixamorig10:LeftArm": [708.71, 408.57], "mixamorig10:LeftForeArm": [726.96, 383.87], "mixamorig10:LeftHand": [718.19, 367.66], "mixamorig10:LeftHandIndex1": [713.71, 364.53], "mixamorig10:LeftHandIndex2": [710.19, 363.21], "mixamorig10:LeftHandIndex3": [706.09, 362.96], "mixamorig10:LeftHandIndex4": [702.25, 363.22], "mixamorig10:LeftHandMiddle1": [713.35, 361.18], "mixamorig10:LeftHandMiddle2": [709.71, 359.80], "mixamorig10:LeftHandMiddle3": [705.18, 359.56], "mixamorig10:LeftHandMiddle4": [700.83, 359.91], "mixamorig10:LeftHandPinky1": [712.20, 356.55], "mixamorig10:LeftHandPinky2": [709.35, 355.21], "mixamorig10:LeftHandPinky3": [706.38, 354.95], "mixamorig10:LeftHandPinky4": [703.72, 355.10], "mixamorig10:LeftHandRing1": [712.56, 358.27], "mixamorig10:LeftHandRing2": [709.55, 357.11], "mixamorig10:LeftHandRing3": [705.98, 356.97], "mixamorig10:LeftHandRing4": [702.72, 357.30], "mixamorig10:LeftHandThumb1": [715.53, 369.35], "mixamorig10:LeftHandThumb2": [712.69, 370.04], "mixamorig10:LeftHandThumb3": [709.36, 368.96], "mixamorig10:LeftHandThumb4": [706.66, 367.46], "mixamorig10:Neck": [678.70, 416.92], "mixamorig10:Head": [676.52, 427.13], "mixamorig10:HeadTop_End": [669.66, 456.54], "mixamorig10:RightShoulder": [669.17, 414.66], "mixamorig10:RightArm": [652.24, 407.14], "mixamorig10:RightForeArm": [637.74, 373.79], "mixamorig10:RightHand": [638.98, 374.55], "mixamorig10:RightHandIndex1": [639.64, 382.29], "mixamorig10:RightHandIndex2": [641.37, 382.65], "mixamorig10:RightHandIndex3": [644.42, 382.55], "mixamorig10:RightHandIndex4": [647.55, 382.29], "mixamorig10:RightHandMiddle1": [637.92, 379.08], "mixamorig10:RightHandMiddle2": [639.75, 379.44], "mixamorig10:RightHandMiddle3": [642.95, 379.33], "mixamorig10:RightHandMiddle4": [646.33, 379.09], "mixamorig10:RightHandPinky1": [636.44, 372.33], "mixamorig10:RightHandPinky2": [637.86, 372.57], "mixamorig10:RightHandPinky3": [640.11, 372.55], "mixamorig10:RightHandPinky4": [642.40, 372.45], "mixamorig10:RightHandRing1": [637.09, 375.88], "mixamorig10:RightHandRing2": [638.62, 376.16], "mixamorig10:RightHandRing3": [641.39, 376.12], "mixamorig10:RightHandRing4": [644.33, 375.98], "mixamorig10:RightHandThumb1": [641.78, 379.02], "mixamorig10:RightHandThumb2": [644.08, 381.92], "mixamorig10:RightHandThumb3": [645.77, 382.68], "mixamorig10:RightHandThumb4": [646.74, 382.93]}}