{"cam1": {"Running_Man": [853.12, 278.95], "Ch28_Body": [853.12, 278.95], "Ch28_Eyelashes": [853.12, 278.95], "Ch28_Hair": [853.12, 278.95], "Ch28_Hoody": [853.12, 278.95], "Ch28_Pants": [853.12, 278.95], "Ch28_Sneakers": [853.12, 278.95], "mixamorig10:Hips": [868.64, 340.20], "mixamorig10:LeftUpLeg": [867.71, 341.43], "mixamorig10:LeftLeg": [878.50, 310.44], "mixamorig10:LeftFoot": [865.11, 284.85], "mixamorig10:LeftToeBase": [876.27, 275.43], "mixamorig10:LeftToe_End": [882.74, 274.49], "mixamorig10:RightUpLeg": [866.08, 331.14], "mixamorig10:RightLeg": [858.30, 301.29], "mixamorig10:RightFoot": [823.47, 303.41], "mixamorig10:RightToeBase": [810.75, 296.02], "mixamorig10:RightToe_End": [809.22, 290.60], "mixamorig10:Spine": [870.40, 347.64], "mixamorig10:Spine1": [873.12, 356.45], "mixamorig10:Spine2": [877.34, 366.97], "mixamorig10:LeftShoulder": [882.04, 381.75], "mixamorig10:LeftArm": [877.62, 384.38], "mixamorig10:LeftForeArm": [857.82, 375.50], "mixamorig10:LeftHand": [874.40, 364.39], "mixamorig10:LeftHandIndex1": [885.20, 361.63], "mixamorig10:LeftHandIndex2": [887.89, 359.83], "mixamorig10:LeftHandIndex3": [890.02, 358.37], "mixamorig10:LeftHandIndex4": [891.68, 357.23], "mixamorig10:LeftHandMiddle1": [883.89, 359.67], "mixamorig10:LeftHandMiddle2": [886.67, 357.81], "mixamorig10:LeftHandMiddle3": [889.02, 356.20], "mixamorig10:LeftHandMiddle4": [890.92, 354.94], "mixamorig10:LeftHandPinky1": [880.69, 356.64], "mixamorig10:LeftHandPinky2": [882.75, 355.03], "mixamorig10:LeftHandPinky3": [884.22, 353.91], "mixamorig10:LeftHandPinky4": [885.33, 353.09], "mixamorig10:LeftHandRing1": [882.86, 357.80], "mixamorig10:LeftHandRing2": [885.16, 356.25], "mixamorig10:LeftHandRing3": [887.05, 355.01], "mixamorig10:LeftHandRing4": [888.51, 354.10], "mixamorig10:LeftHandThumb1": [879.13, 364.56], "mixamorig10:LeftHandThumb2": [882.87, 364.09], "mixamorig10:LeftHandThumb3": [885.75, 362.47], "mixamorig10:LeftHandThumb4": [887.90, 360.82], "mixamorig10:Neck": [883.25, 379.31], "mixamorig10:Head": [889.68, 384.23], "mixamorig10:HeadTop_End": [908.87, 396.86], "mixamorig10:RightShoulder": [883.08, 374.62], "mixamorig10:RightArm": [880.20, 363.62], "mixamorig10:RightForeArm": [872.68, 337.97], "mixamorig10:RightHand": [891.21, 339.66], "mixamorig10:RightHandIndex1": [900.39, 344.99], "mixamorig10:RightHandIndex2": [901.89, 346.11], "mixamorig10:RightHandIndex3": [902.21, 347.44], "mixamorig10:RightHandIndex4": [901.97, 348.65], "mixamorig10:RightHandMiddle1": [900.82, 342.65], "mixamorig10:RightHandMiddle2": [902.41, 343.84], "mixamorig10:RightHandMiddle3": [902.72, 345.25], "mixamorig10:RightHandMiddle4": [902.46, 346.59], "mixamorig10:RightHandPinky1": [899.27, 338.41], "mixamorig10:RightHandPinky2": [900.52, 339.36], "mixamorig10:RightHandPinky3": [900.74, 340.42], "mixamorig10:RightHandPinky4": [900.57, 341.39], "mixamorig10:RightHandRing1": [900.42, 340.62], "mixamorig10:RightHandRing2": [901.76, 341.64], "mixamorig10:RightHandRing3": [902.03, 342.90], "mixamorig10:RightHandRing4": [901.80, 344.11], "mixamorig10:RightHandThumb1": [893.55, 343.54], "mixamorig10:RightHandThumb2": [895.46, 346.29], "mixamorig10:RightHandThumb3": [897.24, 347.62], "mixamorig10:RightHandThumb4": [898.80, 348.32]},  "cam2": {"Running_Man": [458.07, 81.52], "Ch28_Body": [458.07, 81.52], "Ch28_Eyelashes": [458.07, 81.52], "Ch28_Hair": [458.07, 81.52], "Ch28_Hoody": [458.07, 81.52], "Ch28_Pants": [458.07, 81.52], "Ch28_Sneakers": [458.07, 81.52], "mixamorig10:Hips": [462.09, 334.52], "mixamorig10:LeftUpLeg": [484.85, 319.24], "mixamorig10:LeftLeg": [443.63, 202.36], "mixamorig10:LeftFoot": [447.44, 94.00], "mixamorig10:LeftToeBase": [419.19, 41.82], "mixamorig10:LeftToe_End": [404.38, 32.50], "mixamorig10:RightUpLeg": [443.35, 318.08], "mixamorig10:RightLeg": [439.93, 203.21], "mixamorig10:RightFoot": [507.21, 192.47], "mixamorig10:RightToeBase": [519.14, 167.72], "mixamorig10:RightToe_End": [516.34, 151.74], "mixamorig10:Spine": [461.52, 363.58], "mixamorig10:Spine1": [460.02, 397.45], "mixamorig10:Spine2": [458.49, 436.46], "mixamorig10:LeftShoulder": [476.33, 476.56], "mixamorig10:LeftArm": [514.90, 459.66], "mixamorig10:LeftForeArm": [554.42, 399.98], "mixamorig10:LeftHand": [524.94, 375.45], "mixamorig10:LeftHandIndex1": [507.33, 373.14], "mixamorig10:LeftHandIndex2": [497.90, 371.57], "mixamorig10:LeftHandIndex3": [487.96, 372.10], "mixamorig10:LeftHandIndex4": [479.04, 373.49], "mixamorig10:LeftHandMiddle1": [506.87, 365.70], "mixamorig10:LeftHandMiddle2": [497.15, 364.00], "mixamorig10:LeftHandMiddle3": [486.20, 364.62], "mixamorig10:LeftHandMiddle4": [476.09, 366.31], "mixamorig10:LeftHandPinky1": [506.12, 355.09], "mixamorig10:LeftHandPinky2": [498.61, 353.13], "mixamorig10:LeftHandPinky3": [491.54, 353.26], "mixamorig10:LeftHandPinky4": [485.47, 354.10], "mixamorig10:LeftHandRing1": [505.49, 359.33], "mixamorig10:LeftHandRing2": [497.45, 357.87], "mixamorig10:LeftHandRing3": [488.84, 358.44], "mixamorig10:LeftHandRing4": [481.28, 359.84], "mixamorig10:LeftHandThumb1": [516.75, 380.77], "mixamorig10:LeftHandThumb2": [508.56, 383.77], "mixamorig10:LeftHandThumb3": [499.52, 382.84], "mixamorig10:LeftHandThumb4": [492.08, 380.70], "mixamorig10:Neck": [457.29, 481.08], "mixamorig10:Head": [450.02, 503.68], "mixamorig10:HeadTop_End": [422.96, 570.04], "mixamorig10:RightShoulder": [439.24, 477.37], "mixamorig10:RightArm": [408.71, 462.59], "mixamorig10:RightForeArm": [381.13, 399.02], "mixamorig10:RightHand": [371.37, 396.75], "mixamorig10:RightHandIndex1": [372.28, 408.58], "mixamorig10:RightHandIndex2": [376.28, 408.05], "mixamorig10:RightHandIndex3": [383.37, 406.84], "mixamorig10:RightHandIndex4": [390.64, 405.58], "mixamorig10:RightHandMiddle1": [368.63, 401.47], "mixamorig10:RightHandMiddle2": [372.84, 400.81], "mixamorig10:RightHandMiddle3": [380.30, 399.54], "mixamorig10:RightHandMiddle4": [388.15, 398.28], "mixamorig10:RightHandPinky1": [365.84, 387.48], "mixamorig10:RightHandPinky2": [369.09, 386.83], "mixamorig10:RightHandPinky3": [374.30, 386.06], "mixamorig10:RightHandPinky4": [379.61, 385.35], "mixamorig10:RightHandRing1": [367.01, 394.65], "mixamorig10:RightHandRing2": [370.53, 394.03], "mixamorig10:RightHandRing3": [376.96, 393.03], "mixamorig10:RightHandRing4": [383.78, 392.09], "mixamorig10:RightHandThumb1": [377.31, 404.65], "mixamorig10:RightHandThumb2": [382.33, 409.49], "mixamorig10:RightHandThumb3": [386.20, 409.77], "mixamorig10:RightHandThumb4": [388.49, 409.17]}}